opcit/__init__.py
opcit/deposit.py
opcit/fastapi_entry.py
opcit/interstitial.py
opcit/opcit_router.py
opcit/settings.py
opcit/depositors/__init__.py
opcit/depositors/ia.py
tests/__init__.py
tests/test_deposit.py
tests/test_ia.py
opcit-0.1.3.dist-info/METADATA
opcit-0.1.3.dist-info/WHEEL
opcit-0.1.3.dist-info/top_level.txt
opcit-0.1.3.dist-info/RECORD
