Metadata-Version: 2.1
Name: opcit
Version: 0.1.3
Summary: A plugin for Crossref's Labs API that handles digital preservation on Crossref deposits.
Home-page: https://gitlab.com/crossref/labs/opcit
Author: Martin Paul Eve
Author-email: meve@crossref.org
Maintainer-email: Martin Paul Eve <meve@crossref.org>
Project-URL: homepage, https://labs.crossref.org
Project-URL: documentation, https://labs.crossref.org
Project-URL: repository, https://gitlab.com/crossref/labs/opcit
Project-URL: changelog, https://gitlab.com/crossref/labs/opcit/-/blob/main/CHANGELOG.md
Keywords: digital-preservation,academic
Classifier: Development Status :: 4 - Beta
Classifier: Programming Language :: Python
Requires-Python: >=3.8
Requires-Dist: click
Requires-Dist: rich
Requires-Dist: fastapi
Requires-Dist: longsight
Requires-Dist: python-multipart
Requires-Dist: lxml
Requires-Dist: httpx
Requires-Dist: internetarchive
Requires-Dist: claws
Requires-Dist: python-magic
Requires-Dist: clannotation
